quantfreedom/__init__.py
quantfreedom/backtesters/__init__.py
quantfreedom/backtesters/bt_live_bt.py
quantfreedom/backtesters/bt_multi_bt.py
quantfreedom/backtesters/bt_or_bt.py
quantfreedom/core/__init__.py
quantfreedom/core/enums.py
quantfreedom/core/plotting_base.py
quantfreedom/core/strategy.py
quantfreedom/exchanges/__init__.py
quantfreedom/exchanges/binance_usdm.py
quantfreedom/exchanges/bybit.py
quantfreedom/exchanges/exchange.py
quantfreedom/exchanges/mufex.py
quantfreedom/helpers/__init__.py
quantfreedom/helpers/bsc_scan.py
quantfreedom/helpers/custom_logger.py
quantfreedom/helpers/email_sender.py
quantfreedom/helpers/helper_funcs.py
quantfreedom/helpers/utils.py
quantfreedom/indicators/__init__.py
quantfreedom/indicators/tv_indicators.py
quantfreedom/order_handler/__init__.py
quantfreedom/order_handler/increase_position.py
quantfreedom/order_handler/leverage.py
quantfreedom/order_handler/order.py
quantfreedom/order_handler/stop_loss.py
quantfreedom/order_handler/take_profit.py
quantfreedom-0.2.0.4.dist-info/LICENSE
quantfreedom-0.2.0.4.dist-info/METADATA
quantfreedom-0.2.0.4.dist-info/WHEEL
quantfreedom-0.2.0.4.dist-info/RECORD
